CHANGES.rst
DESCRIPTION.rst
LICENSE
MANIFEST.in
README.md
setup.py
src/wai.annotations.coco.egg-info/PKG-INFO
src/wai.annotations.coco.egg-info/SOURCES.txt
src/wai.annotations.coco.egg-info/dependency_links.txt
src/wai.annotations.coco.egg-info/entry_points.txt
src/wai.annotations.coco.egg-info/namespace_packages.txt
src/wai.annotations.coco.egg-info/requires.txt
src/wai.annotations.coco.egg-info/top_level.txt
src/wai/annotations/coco/__init__.py
src/wai/annotations/coco/component/_COCOWriter.py
src/wai/annotations/coco/component/_FromCOCO.py
src/wai/annotations/coco/component/_ToCOCOExternalFormat.py
src/wai/annotations/coco/component/__init__.py
src/wai/annotations/coco/configuration/_Annotation.py
src/wai/annotations/coco/configuration/_COCOFile.py
src/wai/annotations/coco/configuration/_Category.py
src/wai/annotations/coco/configuration/_Image.py
src/wai/annotations/coco/configuration/_Info.py
src/wai/annotations/coco/configuration/_License.py
src/wai/annotations/coco/configuration/__init__.py
src/wai/annotations/coco/specifier/_COCOInputFormatSpecifier.py
src/wai/annotations/coco/specifier/_COCOOutputFormatSpecifier.py
src/wai/annotations/coco/specifier/__init__.py
src/wai/annotations/coco/util/__init__.py
src/wai/annotations/coco/util/_format.py
src/wai/annotations/coco/util/_located_object_to_annotation.py